liquiphy/__init__.py
liquiphy/empty.sfz
liquiphy/quick_liq.py
liquiphy-1.0.10.dist-info/entry_points.txt
liquiphy-1.0.10.dist-info/LICENSE
liquiphy-1.0.10.dist-info/WHEEL
liquiphy-1.0.10.dist-info/METADATA
liquiphy-1.0.10.dist-info/RECORD
