Metadata-Version: 2.1
Name: liquiphy
Version: 1.0.10
Summary: A quick and dirty interface to the liquidsfz command-line using python's subprocess.
Author-email: Leon Dionne <ldionne@dridesign.sh.cn>
Classifier: License :: OSI Approved :: GNU General Public License v3 or later (GPLv3+)
Classifier: Programming Language :: Python
Classifier: Programming Language :: Python :: 3.10
Classifier: Topic :: Multimedia :: Sound/Audio :: Sound Synthesis
Classifier: Topic :: Multimedia :: Sound/Audio :: MIDI
Requires-Dist: conn_jack
Project-URL: Home, https://github.com/Zen-Master-SoSo/liquiphy
